requests_html_playwright/__init__.py
requests_html_playwright/requests_html.py
requests_html_playwright-0.13.0.dist-info/LICENSE
requests_html_playwright-0.13.0.dist-info/METADATA
requests_html_playwright-0.13.0.dist-info/WHEEL
requests_html_playwright-0.13.0.dist-info/RECORD
