Metadata-Version: 2.3
Name: requests-html-playwright
Version: 0.13.0
Summary: Requests-HTML(with microsoft/playwright-python): HTML Parsing for Humans™
License: MIT
Keywords: requests-html,playwright
Author: Asugawara
Author-email: asgasw@gmail.com
Requires-Python: >=3.9,<4.0
Classifier: License :: OSI Approved :: MIT License
Classifier: Programming Language :: Python
Classifier: Programming Language :: Python :: 3
Classifier: Programming Language :: Python :: 3.9
Classifier: Programming Language :: Python :: 3.10
Classifier: Programming Language :: Python :: 3.11
Classifier: Programming Language :: Python :: 3.12
Classifier: Programming Language :: Python :: 3.13
Classifier: Programming Language :: Python :: 3 :: Only
Classifier: Programming Language :: Python :: Implementation :: PyPy
Requires-Dist: beautifulsoup4 (>=4.12.2,<5.0.0)
Requires-Dist: fake-useragent (>=1.5.0,<2.0.0)
Requires-Dist: lxml-html-clean (>=0.4.1,<0.5.0)
Requires-Dist: parse (>=1.19.0,<2.0.0)
Requires-Dist: playwright (>=1.49.0,<2.0.0)
Requires-Dist: pyquery (>=2.0.0,<3.0.0)
Requires-Dist: requests (>=2.32.3,<3.0.0)
Requires-Dist: rfc3986 (>=2.0.0,<3.0.0)
Requires-Dist: w3lib (>=2.2.0,<3.0.0)
Project-URL: Homepage, https://github.com/Asugawara/requests-html-playwright
Project-URL: Repository, https://github.com/Asugawara/requests-html-playwright
